wnpoly/__about__.py
wnpoly/__init__.py
wnpoly/bell.py
wnpoly/symm.py
wnpoly-2.0.2.dist-info/licenses/LICENSE.txt
wnpoly-2.0.2.dist-info/METADATA
wnpoly-2.0.2.dist-info/WHEEL
wnpoly-2.0.2.dist-info/top_level.txt
wnpoly-2.0.2.dist-info/RECORD
