Metadata-Version: 2.4
Name: wnpoly
Version: 2.0.2
Summary: Package to compute useful polynomials for Webnucleo projects.
Author-email: "Bradley S. Meyer" <mbradle@g.clemson.edu>, Ian Reistroffer <ireistr@g.clemson.edu>
Maintainer-email: "Bradley S. Meyer" <mbradle@g.clemson.edu>
License-Expression: GPL-3.0-or-later
Project-URL: Documentation, https://wnpoly.readthedocs.org
Project-URL: Repository, https://github.com/mbradle/wnpoly.git
Project-URL: Bug Tracker, https://github.com/mbradle/wnpoly/issues
Keywords: polynomials,Bell,symmetric
Classifier: Development Status :: 5 - Production/Stable
Classifier: Intended Audience :: Science/Research
Classifier: Topic :: Scientific/Engineering :: Astronomy
Classifier: Programming Language :: Python :: 3
Requires-Python: >=3.0
License-File: LICENSE.txt
Requires-Dist: numpy
Requires-Dist: scipy
Dynamic: license-file
